reunion/__init__.py
reunion/meeting.py
reunion-0.1.2.dist-info/DESCRIPTION.rst
reunion-0.1.2.dist-info/METADATA
reunion-0.1.2.dist-info/RECORD
reunion-0.1.2.dist-info/WHEEL
reunion-0.1.2.dist-info/metadata.json
reunion-0.1.2.dist-info/top_level.txt
